convlab/__init__.py
convlab/base_models/__init__.py
convlab/base_models/bert/create_data.py
convlab/base_models/bert/infer_bio.sh
convlab/base_models/bert/run_token_classification.py
convlab/base_models/bert/seqeval_metric.py
convlab/base_models/bert/train_bio.sh
convlab/base_models/t5/README.md
convlab/base_models/t5/__init__.py
convlab/base_models/t5/create_data.py
convlab/base_models/t5/run_seq2seq.py
convlab/base_models/t5/trainer.py
convlab/base_models/t5/dst/__init__.py
convlab/base_models/t5/dst/dst.py
convlab/base_models/t5/dst/dst_metric.py
convlab/base_models/t5/dst/merge_data.py
convlab/base_models/t5/dst/merge_predict_res.py
convlab/base_models/t5/dst/run_dst.sh
convlab/base_models/t5/dst/run_dst_fewshot.sh
convlab/base_models/t5/dst/run_dst_multitask.sh
convlab/base_models/t5/dst/run_dst_pretrain.sh
convlab/base_models/t5/dst/serialization.py
convlab/base_models/t5/goal2dialogue/run_goal2dialogue.sh
convlab/base_models/t5/nlg/__init__.py
convlab/base_models/t5/nlg/merge_data.py
convlab/base_models/t5/nlg/merge_predict_res.py
convlab/base_models/t5/nlg/nlg.py
convlab/base_models/t5/nlg/nlg_metric.py
convlab/base_models/t5/nlg/run_nlg.sh
convlab/base_models/t5/nlg/run_nlg_fewshot.sh
convlab/base_models/t5/nlg/run_nlg_multitask.sh
convlab/base_models/t5/nlg/run_nlg_pretrain.sh
convlab/base_models/t5/nlu/__init__.py
convlab/base_models/t5/nlu/merge_data.py
convlab/base_models/t5/nlu/merge_predict_res.py
convlab/base_models/t5/nlu/nlu.py
convlab/base_models/t5/nlu/nlu_metric.py
convlab/base_models/t5/nlu/run_nlu.sh
convlab/base_models/t5/nlu/run_nlu_fewshot.sh
convlab/base_models/t5/nlu/run_nlu_multitask.sh
convlab/base_models/t5/nlu/run_nlu_pretrain.sh
convlab/base_models/t5/nlu/run_retnlu.sh
convlab/base_models/t5/nlu/run_retnlu_fewshot.sh
convlab/base_models/t5/nlu/run_retnlu_in_context.sh
convlab/base_models/t5/nlu/run_retnlu_in_context_fewshot.sh
convlab/base_models/t5/nlu/serialization.py
convlab/base_models/t5/rg/run_rg.sh
convlab/deploy/README.md
convlab-3.0.0.dev20221130.dist-info/LICENSE
convlab-3.0.0.dev20221130.dist-info/METADATA
convlab-3.0.0.dev20221130.dist-info/NOTICE
convlab-3.0.0.dev20221130.dist-info/WHEEL
convlab-3.0.0.dev20221130.dist-info/top_level.txt
convlab-3.0.0.dev20221130.dist-info/RECORD
