Metadata-Version: 2.1
Name: convlab
Version: 3.0.0.dev20221130
Summary: An Open-source Dialog System Toolkit
Home-page: https://github.com/ConvLab/ConvLab-3
Author: convlab
Author-email: convlab@googlegroups.com
License: Apache
Classifier: Development Status :: 3 - Alpha
Classifier: License :: OSI Approved :: Apache Software License
Classifier: Programming Language :: Python :: 3.8
Classifier: Programming Language :: Python :: 3.9
Classifier: Intended Audience :: Science/Research
Classifier: Intended Audience :: Developers
Classifier: Topic :: Scientific/Engineering :: Artificial Intelligence
Requires-Python: >=3.8
License-File: LICENSE
License-File: NOTICE
Requires-Dist: joblib (>=1.2.0)
Requires-Dist: pillow (>=9.3.0)
Requires-Dist: protobuf (>=3.20.2)
Requires-Dist: oauthlib (>=3.2.1)
Requires-Dist: accelerate
Requires-Dist: rouge-score
Requires-Dist: sacrebleu
Requires-Dist: tensorboardX
Requires-Dist: boto3
Requires-Dist: matplotlib
Requires-Dist: seaborn
Requires-Dist: tabulate
Requires-Dist: python-Levenshtein
Requires-Dist: requests
Requires-Dist: numpy
Requires-Dist: nltk
Requires-Dist: scipy
Requires-Dist: tensorboard
Requires-Dist: torch (<=1.13,>=1.10.1)
Requires-Dist: transformers (<=4.24.0,>=4.17.0)
Requires-Dist: sentence-transformers (>=2.2.2)
Requires-Dist: datasets (>=2.0)
Requires-Dist: seqeval
Requires-Dist: spacy
Requires-Dist: simplejson
Requires-Dist: unidecode
Requires-Dist: jieba
Requires-Dist: embeddings
Requires-Dist: visdom
Requires-Dist: quadprog
Requires-Dist: fuzzywuzzy
Requires-Dist: json-lines
Requires-Dist: gtts
Requires-Dist: deepspeech
Requires-Dist: pydub
Provides-Extra: develop
Requires-Dist: python-coveralls ; extra == 'develop'
Requires-Dist: pytest-dependency ; extra == 'develop'
Requires-Dist: pytest-mock ; extra == 'develop'
Requires-Dist: requests-mock ; extra == 'develop'
Requires-Dist: pytest ; extra == 'develop'
Requires-Dist: pytest-cov ; extra == 'develop'
Requires-Dist: checksumdir ; extra == 'develop'
Requires-Dist: bs4 ; extra == 'develop'
Requires-Dist: lxml ; extra == 'develop'
